LICENSE.md
MANIFEST.in
README.md
requirements.txt
setup.py
ncbitaxonomy/__init__.py
ncbitaxonomy/citation.py
ncbitaxonomy/utils.py
ncbitaxonomy.egg-info/PKG-INFO
ncbitaxonomy.egg-info/SOURCES.txt
ncbitaxonomy.egg-info/dependency_links.txt
ncbitaxonomy.egg-info/not-zip-safe
ncbitaxonomy.egg-info/requires.txt
ncbitaxonomy.egg-info/top_level.txt
ncbitaxonomy/coretype/__init__.py
ncbitaxonomy/coretype/seqgroup.py
ncbitaxonomy/coretype/tree.py
ncbitaxonomy/ncbi_taxonomy/__init__.py
ncbitaxonomy/ncbi_taxonomy/ncbiquery.py
ncbitaxonomy/ncbi_taxonomy/ncbiquery2.py
ncbitaxonomy/parser/__init__.py
ncbitaxonomy/parser/fasta.py
ncbitaxonomy/parser/newick.py
ncbitaxonomy/parser/paml.py
ncbitaxonomy/parser/phylip.py
ncbitaxonomy/phylo/__init__.py
ncbitaxonomy/phylo/evolevents.py
ncbitaxonomy/phylo/phylotree.py
ncbitaxonomy/phylo/reconciliation.py
ncbitaxonomy/phylo/spoverlap.py