Metadata-Version: 2.1
Name: ncbitaxonomy
Version: 3.1.2.post3
Summary: The basic NCBI taxonomy functionality from ETE3
Home-page: UNKNOWN
Author: awright
Author-email: awright@nanoporetech.com
License: UNKNOWN
Keywords: tree,tree reconstruction,tree visualization,tree comparison,phylogeny,phylogenetics,phylogenomics
Platform: UNKNOWN
Classifier: Development Status :: 6 - Mature
Classifier: Environment :: Console
Classifier: Environment :: X11 Applications :: Qt
Classifier: Intended Audience :: Developers
Classifier: Intended Audience :: Other Audience
Classifier: Intended Audience :: Science/Research
Classifier: License :: OSI Approved :: GNU General Public License (GPL)
Classifier: Natural Language :: English
Classifier: Operating System :: MacOS
Classifier: Operating System :: Microsoft :: Windows
Classifier: Operating System :: POSIX :: Linux
Classifier: Programming Language :: Python
Classifier: Topic :: Scientific/Engineering :: Bio-Informatics
Classifier: Topic :: Scientific/Engineering :: Visualization
Classifier: Topic :: Software Development :: Libraries :: Python Modules
Requires-Python: >=3.5.2
